[
  {
    "py/object": "model.group.Group",
    "footer": "",
    "header": "",
    "id": null,
    "name": ""
  },
  {
    "py/object": "model.group.Group",
    "footer": "footer  ?|^?",
    "header": "headerMoNyQnb[eZO  @{T0Do",
    "id": null,
    "name": "namelQ"
  },
  {
    "py/object": "model.group.Group",
    "footer": "footerCd4Vz{ w",
    "header": "header",
    "id": null,
    "name": "name0"
  },
  {
    "py/object": "model.group.Group",
    "footer": "footerA p,K]? m ,",
    "header": "header0iP[}2L",
    "id": null,
    "name": "nameX6"
  },
  {
    "py/object": "model.group.Group",
    "footer": "footer% 4(|:}WIY1Dcw ~",
    "header": "header2&{q)",
    "id": null,
    "name": "namea"
  },
  {
    "py/object": "model.group.Group",
    "footer": "footerX Mf uP3&c9ug|",
    "header": "header!y#rSjs;A@ />[~]|mG",
    "id": null,
    "name": "name"
  }
]